[
  {
    "meps_id": "MEPS-14939",
    "task_name_sv": "Täck och maskera golv",
    "unit": "m2",
    "labor_norm_per_unit": 0.08,
    "surface_type": "golv",
    "synonyms": "täck och maskera golv;täckmåla och maskera golv;måla och maskera golv;målning och maskera golv;täck och maskning golv;täck och täcka golv;maskera golv;maskera golvet",
    "price_labor_per_hour": 450,
    "price_material_per_unit": 16.2267,
    "material_factor_per_unit": 0.10400000000000001
  },
  {
    "meps_id": "MEPS-14940",
    "task_name_sv": "Flytta ut det genomsnittliga vardagsrumsinnehållet och återställ sedan innehållet i rummet",
    "unit": "st",
    "labor_norm_per_unit": 1.98,
    "synonyms": "flytta ut det genomsnittliga vardagsrumsinnehållet och återställ sedan innehållet i rummet",
    "price_labor_per_hour": 450,
    "price_material_per_unit": 0,
    "material_factor_per_unit": 2.574
  },
  {
    "meps_id": "MEPS-14942",
    "task_name_sv": "Fönster, karm och smyg 0,9–1,7 m² – målning med täckfärg 2 strykningar",
    "unit": "st",
    "labor_norm_per_unit": 0.93,
    "surface_type": "dörr",
    "default_layers": 2,
    "synonyms": "fönster, karm och smyg 0,9–1,7 m² – målning med täckfärg 2 strykningar;fönster, karm och smyg 0,9–1,7 m² – målning med täckmålafärg 2 strykningar;fönster, karm och smyg 0,9–1,7 m² – målning med målafärg 2 strykningar;fönster, karm och smyg 0,9–1,7 m² – målning med målningfärg 2 strykningar;fönster, karm och smyg 0,9–1,7 m² – måla med täckfärg 2 strykningar;fönster, karm och smyg 0,9–1,7 m² – täckmåla med täckfärg 2 strykningar;fönster, karm och smyg 0,9–1,7 m² – färg med täckfärg 2 strykningar;måla dörr;måla dörren;måla dörrar;måla dörrarna",
    "price_labor_per_hour": 450,
    "price_material_per_unit": 95,
    "material_factor_per_unit": 1.209
  },
  {
    "meps_id": "MEPS-1951523",
    "task_name_sv": "Dörrblad, slät, i- och påspackling samt slipning",
    "unit": "st",
    "labor_norm_per_unit": 0.2,
    "surface_type": "dörr",
    "synonyms": "dörrblad, slät, i- och påspackling samt slipning;måla dörr;måla dörren;måla dörrar;måla dörrarna",
    "price_labor_per_hour": 450,
    "price_material_per_unit": 40,
    "material_factor_per_unit": 0.26
  },
  {
    "meps_id": "MEPS-1981523",
    "task_name_sv": "Dörrblad, slät, bredspackling samt slipning, 1 gång",
    "unit": "st",
    "labor_norm_per_unit": 0.3,
    "surface_type": "dörr",
    "synonyms": "dörrblad, slät, bredspackling samt slipning, 1 gång;måla dörr;måla dörren;måla dörrar;måla dörrarna",
    "price_labor_per_hour": 450,
    "price_material_per_unit": 240,
    "material_factor_per_unit": 0.39
  },
  {
    "meps_id": "MEPS-1981524",
    "task_name_sv": "Dörrblad, slät, bredspackling samt slipning, 2 gånger",
    "unit": "st",
    "labor_norm_per_unit": 0.41,
    "surface_type": "dörr",
    "synonyms": "dörrblad, slät, bredspackling samt slipning, 2 gånger;måla dörr;måla dörren;måla dörrar;måla dörrarna",
    "price_labor_per_hour": 450,
    "price_material_per_unit": 391,
    "material_factor_per_unit": 0.533
  },
  {
    "meps_id": "MEPS-1981525",
    "task_name_sv": "Dörrblad, slät, grundning, 1 strykning",
    "unit": "st",
    "labor_norm_per_unit": 0.14,
    "surface_type": "dörr",
    "default_layers": 1,
    "synonyms": "dörrblad, slät, grundning, 1 strykning;måla dörr;måla dörren;måla dörrar;måla dörrarna",
    "price_labor_per_hour": 450,
    "price_material_per_unit": 47,
    "material_factor_per_unit": 0.18200000000000002
  },
  {
    "meps_id": "MEPS-1981526",
    "task_name_sv": "Dörrblad, slät, schellackering, kvistlack",
    "unit": "st",
    "labor_norm_per_unit": 0.07,
    "surface_type": "dörr",
    "synonyms": "dörrblad, slät, schellackering, kvistlack;måla dörr;måla dörren;måla dörrar;måla dörrarna",
    "price_labor_per_hour": 450,
    "price_material_per_unit": 35,
    "material_factor_per_unit": 0.09100000000000001
  },
  {
    "meps_id": "MEPS-1981527",
    "task_name_sv": "Dörrblad, slät, målning, 1 strykning",
    "unit": "st",
    "labor_norm_per_unit": 0.35,
    "surface_type": "dörr",
    "default_layers": 1,
    "synonyms": "dörrblad, slät, målning, 1 strykning;dörrblad, slät, måla, 1 strykning;dörrblad, slät, täckmåla, 1 strykning;dörrblad, slät, färg, 1 strykning;måla dörr;måla dörren;måla dörrar;måla dörrarna",
    "price_labor_per_hour": 450,
    "price_material_per_unit": 74,
    "material_factor_per_unit": 0.45499999999999996
  },
  {
    "meps_id": "MEPS-1981528",
    "task_name_sv": "Dörrblad, slät, målning, 2 strykningar",
    "unit": "st",
    "labor_norm_per_unit": 0.45,
    "surface_type": "dörr",
    "default_layers": 2,
    "synonyms": "dörrblad, slät, målning, 2 strykningar;dörrblad, slät, måla, 2 strykningar;dörrblad, slät, täckmåla, 2 strykningar;dörrblad, slät, färg, 2 strykningar;måla dörr;måla dörren;måla dörrar;måla dörrarna",
    "price_labor_per_hour": 450,
    "price_material_per_unit": 130,
    "material_factor_per_unit": 0.5850000000000001
  },
  {
    "meps_id": "MEPS-1981529",
    "task_name_sv": "Dörrblad, slät, målning, 3 strykningar",
    "unit": "st",
    "labor_norm_per_unit": 0.59,
    "surface_type": "dörr",
    "default_layers": 3,
    "synonyms": "dörrblad, slät, målning, 3 strykningar;dörrblad, slät, måla, 3 strykningar;dörrblad, slät, täckmåla, 3 strykningar;dörrblad, slät, färg, 3 strykningar;måla dörr;måla dörren;måla dörrar;måla dörrarna",
    "price_labor_per_hour": 450,
    "price_material_per_unit": 186,
    "material_factor_per_unit": 0.767
  },
  {
    "meps_id": "MEPS-1981530",
    "task_name_sv": "Dörrblad, slät, lackning, 1 strykning",
    "unit": "st",
    "labor_norm_per_unit": 0.18,
    "surface_type": "dörr",
    "default_layers": 1,
    "synonyms": "dörrblad, slät, lackning, 1 strykning;måla dörr;måla dörren;måla dörrar;måla dörrarna",
    "price_labor_per_hour": 450,
    "price_material_per_unit": 73,
    "material_factor_per_unit": 0.23399999999999999
  },
  {
    "meps_id": "MEPS-1981531",
    "task_name_sv": "Dörrblad, slät, lackning, 2 strykningar",
    "unit": "st",
    "labor_norm_per_unit": 0.23,
    "surface_type": "dörr",
    "default_layers": 2,
    "synonyms": "dörrblad, slät, lackning, 2 strykningar;måla dörr;måla dörren;måla dörrar;måla dörrarna",
    "price_labor_per_hour": 450,
    "price_material_per_unit": 131,
    "material_factor_per_unit": 0.29900000000000004
  },
  {
    "meps_id": "MEPS-1981532",
    "task_name_sv": "Dörrblad, slät, lackning, 3 strykningar",
    "unit": "st",
    "labor_norm_per_unit": 0.28,
    "surface_type": "dörr",
    "default_layers": 3,
    "synonyms": "dörrblad, slät, lackning, 3 strykningar;måla dörr;måla dörren;måla dörrar;måla dörrarna",
    "price_labor_per_hour": 450,
    "price_material_per_unit": 187,
    "material_factor_per_unit": 0.36400000000000005
  },
  {
    "meps_id": "MEPS-2011523",
    "task_name_sv": "Dörrblad, slät, lasering, 1 strykning",
    "unit": "st",
    "labor_norm_per_unit": 0.18,
    "surface_type": "dörr",
    "default_layers": 1,
    "synonyms": "dörrblad, slät, lasering, 1 strykning;måla dörr;måla dörren;måla dörrar;måla dörrarna",
    "price_labor_per_hour": 450,
    "price_material_per_unit": 144,
    "material_factor_per_unit": 0.23399999999999999
  },
  {
    "meps_id": "MEPS-2011524",
    "task_name_sv": "Dörrblad, slät, lasering, 2 strykningar",
    "unit": "st",
    "labor_norm_per_unit": 0.23,
    "surface_type": "dörr",
    "default_layers": 2,
    "synonyms": "dörrblad, slät, lasering, 2 strykningar;måla dörr;måla dörren;måla dörrar;måla dörrarna",
    "price_labor_per_hour": 450,
    "price_material_per_unit": 254,
    "material_factor_per_unit": 0.29900000000000004
  },
  {
    "meps_id": "MEPS-2011525",
    "task_name_sv": "Dörrblad, slät, lasering, 3 strykningar",
    "unit": "st",
    "labor_norm_per_unit": 0.28,
    "surface_type": "dörr",
    "default_layers": 3,
    "synonyms": "dörrblad, slät, lasering, 3 strykningar;måla dörr;måla dörren;måla dörrar;måla dörrarna",
    "price_labor_per_hour": 450,
    "price_material_per_unit": 367,
    "material_factor_per_unit": 0.36400000000000005
  },
  {
    "meps_id": "MEPS-2011526",
    "task_name_sv": "Dörrblad, slät, oljning, 1 strykning",
    "unit": "st",
    "labor_norm_per_unit": 0.15,
    "surface_type": "dörr",
    "default_layers": 1,
    "synonyms": "dörrblad, slät, oljning, 1 strykning;måla dörr;måla dörren;måla dörrar;måla dörrarna",
    "price_labor_per_hour": 450,
    "price_material_per_unit": 89,
    "material_factor_per_unit": 0.195
  },
  {
    "meps_id": "MEPS-2011527",
    "task_name_sv": "Dörrblad, slät, oljning, 2 strykningar",
    "unit": "st",
    "labor_norm_per_unit": 0.2,
    "surface_type": "dörr",
    "default_layers": 2,
    "synonyms": "dörrblad, slät, oljning, 2 strykningar;måla dörr;måla dörren;måla dörrar;måla dörrarna",
    "price_labor_per_hour": 450,
    "price_material_per_unit": 144,
    "material_factor_per_unit": 0.26
  },
  {
    "meps_id": "MEPS-2041523",
    "task_name_sv": "Dörrblad, profil, i- och påspackling samt slipning",
    "unit": "st",
    "labor_norm_per_unit": 0.31,
    "surface_type": "dörr",
    "synonyms": "dörrblad, profil, i- och påspackling samt slipning;måla dörr;måla dörren;måla dörrar;måla dörrarna",
    "price_labor_per_hour": 450,
    "price_material_per_unit": 150,
    "material_factor_per_unit": 0.403
  },
  {
    "meps_id": "MEPS-2041524",
    "task_name_sv": "Dörrblad, profil, bredspackling samt slipning, 1 gång",
    "unit": "st",
    "labor_norm_per_unit": 0.47,
    "surface_type": "dörr",
    "synonyms": "dörrblad, profil, bredspackling samt slipning, 1 gång;måla dörr;måla dörren;måla dörrar;måla dörrarna",
    "price_labor_per_hour": 450,
    "price_material_per_unit": 240,
    "material_factor_per_unit": 0.611
  },
  {
    "meps_id": "MEPS-2041525",
    "task_name_sv": "Dörrblad, profil, bredspackling samt slipning, 2 gånger",
    "unit": "st",
    "labor_norm_per_unit": 0.89,
    "surface_type": "dörr",
    "synonyms": "dörrblad, profil, bredspackling samt slipning, 2 gånger;måla dörr;måla dörren;måla dörrar;måla dörrarna",
    "price_labor_per_hour": 450,
    "price_material_per_unit": 391,
    "material_factor_per_unit": 1.157
  },
  {
    "meps_id": "MEPS-2041526",
    "task_name_sv": "Dörrblad, profil, grundning, 1 strykning",
    "unit": "st",
    "labor_norm_per_unit": 0.2,
    "surface_type": "dörr",
    "default_layers": 1,
    "synonyms": "dörrblad, profil, grundning, 1 strykning;måla dörr;måla dörren;måla dörrar;måla dörrarna",
    "price_labor_per_hour": 450,
    "price_material_per_unit": 48,
    "material_factor_per_unit": 0.26
  },
  {
    "meps_id": "MEPS-2041527",
    "task_name_sv": "Dörrblad, profil, målning, 1 strykning",
    "unit": "st",
    "labor_norm_per_unit": 0.49,
    "surface_type": "dörr",
    "default_layers": 1,
    "synonyms": "dörrblad, profil, målning, 1 strykning;dörrblad, profil, måla, 1 strykning;dörrblad, profil, täckmåla, 1 strykning;dörrblad, profil, färg, 1 strykning;måla dörr;måla dörren;måla dörrar;måla dörrarna",
    "price_labor_per_hour": 450,
    "price_material_per_unit": 72,
    "material_factor_per_unit": 0.637
  },
  {
    "meps_id": "MEPS-2041528",
    "task_name_sv": "Dörrblad, profil, målning, 2 strykningar",
    "unit": "st",
    "labor_norm_per_unit": 0.71,
    "surface_type": "dörr",
    "default_layers": 2,
    "synonyms": "dörrblad, profil, målning, 2 strykningar;dörrblad, profil, måla, 2 strykningar;dörrblad, profil, täckmåla, 2 strykningar;dörrblad, profil, färg, 2 strykningar;måla dörr;måla dörren;måla dörrar;måla dörrarna",
    "price_labor_per_hour": 450,
    "price_material_per_unit": 128,
    "material_factor_per_unit": 0.9229999999999999
  },
  {
    "meps_id": "MEPS-2071523",
    "task_name_sv": "Dörrblad, profil, lackning, 1 strykning",
    "unit": "st",
    "labor_norm_per_unit": 0.24,
    "surface_type": "dörr",
    "default_layers": 1,
    "synonyms": "dörrblad, profil, lackning, 1 strykning;måla dörr;måla dörren;måla dörrar;måla dörrarna",
    "price_labor_per_hour": 450,
    "price_material_per_unit": 73,
    "material_factor_per_unit": 0.312
  },
  {
    "meps_id": "MEPS-2071524",
    "task_name_sv": "Dörrblad, profil, lackning, 2 strykningar",
    "unit": "st",
    "labor_norm_per_unit": 0.31,
    "surface_type": "dörr",
    "default_layers": 2,
    "synonyms": "dörrblad, profil, lackning, 2 strykningar;måla dörr;måla dörren;måla dörrar;måla dörrarna",
    "price_labor_per_hour": 450,
    "price_material_per_unit": 131,
    "material_factor_per_unit": 0.403
  },
  {
    "meps_id": "MEPS-2071525",
    "task_name_sv": "Dörrblad, profil, lackning, 3 strykningar",
    "unit": "st",
    "labor_norm_per_unit": 0.41,
    "surface_type": "dörr",
    "default_layers": 3,
    "synonyms": "dörrblad, profil, lackning, 3 strykningar;måla dörr;måla dörren;måla dörrar;måla dörrarna",
    "price_labor_per_hour": 450,
    "price_material_per_unit": 187,
    "material_factor_per_unit": 0.533
  },
  {
    "meps_id": "MEPS-2071526",
    "task_name_sv": "Dörrblad, profil, lasering, 1 strykning",
    "unit": "st",
    "labor_norm_per_unit": 0.24,
    "surface_type": "dörr",
    "default_layers": 1,
    "synonyms": "dörrblad, profil, lasering, 1 strykning;måla dörr;måla dörren;måla dörrar;måla dörrarna",
    "price_labor_per_hour": 450,
    "price_material_per_unit": 144,
    "material_factor_per_unit": 0.312
  },
  {
    "meps_id": "MEPS-2071527",
    "task_name_sv": "Dörrblad, profil, lasering, 2 strykningar",
    "unit": "st",
    "labor_norm_per_unit": 0.31,
    "surface_type": "dörr",
    "default_layers": 2,
    "synonyms": "dörrblad, profil, lasering, 2 strykningar;måla dörr;måla dörren;måla dörrar;måla dörrarna",
    "price_labor_per_hour": 450,
    "price_material_per_unit": 256,
    "material_factor_per_unit": 0.403
  },
  {
    "meps_id": "MEPS-2071528",
    "task_name_sv": "Dörrblad, profil, lasering, 3 strykningar",
    "unit": "st",
    "labor_norm_per_unit": 0.41,
    "surface_type": "dörr",
    "default_layers": 3,
    "synonyms": "dörrblad, profil, lasering, 3 strykningar;måla dörr;måla dörren;måla dörrar;måla dörrarna",
    "price_labor_per_hour": 450,
    "price_material_per_unit": 367,
    "material_factor_per_unit": 0.533
  },
  {
    "meps_id": "MEPS-2371523",
    "task_name_sv": "Karm, smyg och foder, i- och påspackling samt slipning",
    "unit": "st",
    "labor_norm_per_unit": 0.15,
    "surface_type": "dörr",
    "synonyms": "karm, smyg och foder, i- och påspackling samt slipning;måla dörr;måla dörren;måla dörrar;måla dörrarna",
    "price_labor_per_hour": 450,
    "price_material_per_unit": 20,
    "material_factor_per_unit": 0.195
  },
  {
    "meps_id": "MEPS-2371524",
    "task_name_sv": "Karm, smyg och foder, bredspackling samt slipning, 1 gång",
    "unit": "st",
    "labor_norm_per_unit": 0.18,
    "surface_type": "dörr",
    "synonyms": "karm, smyg och foder, bredspackling samt slipning, 1 gång;måla dörr;måla dörren;måla dörrar;måla dörrarna",
    "price_labor_per_hour": 450,
    "price_material_per_unit": 120,
    "material_factor_per_unit": 0.23399999999999999
  },
  {
    "meps_id": "MEPS-2371525",
    "task_name_sv": "Karm, smyg och foder, bredspackling samt slipning, 2 gånger",
    "unit": "st",
    "labor_norm_per_unit": 0.24,
    "surface_type": "dörr",
    "synonyms": "karm, smyg och foder, bredspackling samt slipning, 2 gånger;måla dörr;måla dörren;måla dörrar;måla dörrarna",
    "price_labor_per_hour": 450,
    "price_material_per_unit": 195,
    "material_factor_per_unit": 0.312
  },
  {
    "meps_id": "MEPS-2371526",
    "task_name_sv": "Dörr, karm, smyg och foder, slät, i- och påspackling samt slipning",
    "unit": "st",
    "labor_norm_per_unit": 0.35,
    "surface_type": "dörr",
    "synonyms": "dörr, karm, smyg och foder, slät, i- och påspackling samt slipning;måla dörr;måla dörren;måla dörrar;måla dörrarna",
    "price_labor_per_hour": 450,
    "price_material_per_unit": 60,
    "material_factor_per_unit": 0.45499999999999996
  },
  {
    "meps_id": "MEPS-2371527",
    "task_name_sv": "Dörr, karm, smyg och foder, slät, bredspackling samt slipning, 1 gång",
    "unit": "st",
    "labor_norm_per_unit": 0.45,
    "surface_type": "dörr",
    "synonyms": "dörr, karm, smyg och foder, slät, bredspackling samt slipning, 1 gång;måla dörr;måla dörren;måla dörrar;måla dörrarna",
    "price_labor_per_hour": 450,
    "price_material_per_unit": 360,
    "material_factor_per_unit": 0.5850000000000001
  },
  {
    "meps_id": "MEPS-2401523",
    "task_name_sv": "Dörr, karm, smyg och foder, slät, bredspackling samt slipning, 2 gånger",
    "unit": "st",
    "labor_norm_per_unit": 0.65,
    "surface_type": "dörr",
    "synonyms": "dörr, karm, smyg och foder, slät, bredspackling samt slipning, 2 gånger;måla dörr;måla dörren;måla dörrar;måla dörrarna",
    "price_labor_per_hour": 450,
    "price_material_per_unit": 391,
    "material_factor_per_unit": 0.8450000000000001
  },
  {
    "meps_id": "MEPS-2401524",
    "task_name_sv": "Dörr, karm, smyg och foder, profil, i- och påspackling samt slipning",
    "unit": "st",
    "labor_norm_per_unit": 0.45,
    "surface_type": "dörr",
    "synonyms": "dörr, karm, smyg och foder, profil, i- och påspackling samt slipning;måla dörr;måla dörren;måla dörrar;måla dörrarna",
    "price_labor_per_hour": 450,
    "price_material_per_unit": 190,
    "material_factor_per_unit": 0.5850000000000001
  },
  {
    "meps_id": "MEPS-2431523",
    "task_name_sv": "Dörr, karm, smyg och foder, profil, bredspackling samt slipning, 1 gång",
    "unit": "st",
    "labor_norm_per_unit": 0.77,
    "surface_type": "dörr",
    "synonyms": "dörr, karm, smyg och foder, profil, bredspackling samt slipning, 1 gång;måla dörr;måla dörren;måla dörrar;måla dörrarna",
    "price_labor_per_hour": 450,
    "price_material_per_unit": 360,
    "material_factor_per_unit": 1.0010000000000001
  },
  {
    "meps_id": "MEPS-2431524",
    "task_name_sv": "Dörr, karm, smyg och foder, profil, bredspackling samt slipning, 2 gånger",
    "unit": "st",
    "labor_norm_per_unit": 1.13,
    "surface_type": "dörr",
    "synonyms": "dörr, karm, smyg och foder, profil, bredspackling samt slipning, 2 gånger;måla dörr;måla dörren;måla dörrar;måla dörrarna",
    "price_labor_per_hour": 450,
    "price_material_per_unit": 586,
    "material_factor_per_unit": 1.4689999999999999
  },
  {
    "meps_id": "MEPS-2461523",
    "task_name_sv": "Dörr, karm, smyg och foder, slät, grundning, 1 strykning",
    "unit": "st",
    "labor_norm_per_unit": 0.21,
    "surface_type": "dörr",
    "default_layers": 1,
    "synonyms": "dörr, karm, smyg och foder, slät, grundning, 1 strykning;måla dörr;måla dörren;måla dörrar;måla dörrarna",
    "price_labor_per_hour": 450,
    "price_material_per_unit": 75,
    "material_factor_per_unit": 0.273
  },
  {
    "meps_id": "MEPS-2461524",
    "task_name_sv": "Dörr, karm, smyg och foder, slät, schellackering, kvistlack",
    "unit": "st",
    "labor_norm_per_unit": 0.11,
    "surface_type": "dörr",
    "synonyms": "dörr, karm, smyg och foder, slät, schellackering, kvistlack;måla dörr;måla dörren;måla dörrar;måla dörrarna",
    "price_labor_per_hour": 450,
    "price_material_per_unit": 49,
    "material_factor_per_unit": 0.14300000000000002
  },
  {
    "meps_id": "MEPS-2491523",
    "task_name_sv": "Dörr, karm, smyg och foder, slät, målning, 1 strykning",
    "unit": "st",
    "labor_norm_per_unit": 0.56,
    "surface_type": "dörr",
    "default_layers": 1,
    "synonyms": "dörr, karm, smyg och foder, slät, målning, 1 strykning;dörr, karm, smyg och foder, slät, måla, 1 strykning;dörr, karm, smyg och foder, slät, täckmåla, 1 strykning;dörr, karm, smyg och foder, slät, färg, 1 strykning;måla dörr;måla dörren;måla dörrar;måla dörrarna",
    "price_labor_per_hour": 450,
    "price_material_per_unit": 118,
    "material_factor_per_unit": 0.7280000000000001
  },
  {
    "meps_id": "MEPS-2521524",
    "task_name_sv": "Dörr, karm, smyg och foder, slät, målning, 3 strykningar",
    "unit": "st",
    "labor_norm_per_unit": 0.944,
    "surface_type": "dörr",
    "default_layers": 3,
    "synonyms": "dörr, karm, smyg och foder, slät, målning, 3 strykningar;dörr, karm, smyg och foder, slät, måla, 3 strykningar;dörr, karm, smyg och foder, slät, täckmåla, 3 strykningar;dörr, karm, smyg och foder, slät, färg, 3 strykningar;måla dörr;måla dörren;måla dörrar;måla dörrarna",
    "price_labor_per_hour": 450,
    "price_material_per_unit": 306,
    "material_factor_per_unit": 1.2272
  },
  {
    "meps_id": "MEPS-2521525",
    "task_name_sv": "Dörr, karm, smyg och foder, profil, målning, 1 strykning",
    "unit": "st",
    "labor_norm_per_unit": 0.7,
    "surface_type": "dörr",
    "default_layers": 1,
    "synonyms": "dörr, karm, smyg och foder, profil, målning, 1 strykning;dörr, karm, smyg och foder, profil, måla, 1 strykning;dörr, karm, smyg och foder, profil, täckmåla, 1 strykning;dörr, karm, smyg och foder, profil, färg, 1 strykning;måla dörr;måla dörren;måla dörrar;måla dörrarna",
    "price_labor_per_hour": 450,
    "price_material_per_unit": 115,
    "material_factor_per_unit": 0.9099999999999999
  },
  {
    "meps_id": "MEPS-2521526",
    "task_name_sv": "Dörr, karm, smyg och foder, profil, målning, 2 strykningar",
    "unit": "st",
    "labor_norm_per_unit": 0.98,
    "surface_type": "dörr",
    "default_layers": 2,
    "synonyms": "dörr, karm, smyg och foder, profil, målning, 2 strykningar;dörr, karm, smyg och foder, profil, måla, 2 strykningar;dörr, karm, smyg och foder, profil, täckmåla, 2 strykningar;dörr, karm, smyg och foder, profil, färg, 2 strykningar;måla dörr;måla dörren;måla dörrar;måla dörrarna",
    "price_labor_per_hour": 450,
    "price_material_per_unit": 204,
    "material_factor_per_unit": 1.274
  },
  {
    "meps_id": "MEPS-2551524",
    "task_name_sv": "Innervägg, i- och påspackling samt slipning, 1 gång",
    "unit": "m2",
    "labor_norm_per_unit": 0.03,
    "surface_type": "vägg",
    "synonyms": "innervägg, i- och påspackling samt slipning, 1 gång;måla vägg;måla väggar;måla väggen;måla väggarna",
    "price_labor_per_hour": 450,
    "price_material_per_unit": 8.4,
    "material_factor_per_unit": 0.039
  },
  {
    "meps_id": "MEPS-2581523",
    "task_name_sv": "Innervägg, skarvspackling samt slipning",
    "unit": "m2",
    "labor_norm_per_unit": 0.02,
    "surface_type": "vägg",
    "synonyms": "innervägg, skarvspackling samt slipning;måla vägg;måla väggar;måla väggen;måla väggarna",
    "price_labor_per_hour": 450,
    "price_material_per_unit": 5.6,
    "material_factor_per_unit": 0.026000000000000002
  },
  {
    "meps_id": "MEPS-2611523",
    "task_name_sv": "Innervägg, skarvspackling med remsa",
    "unit": "m2",
    "labor_norm_per_unit": 0.08,
    "surface_type": "vägg",
    "synonyms": "innervägg, skarvspackling med remsa;måla vägg;måla väggar;måla väggen;måla väggarna",
    "price_labor_per_hour": 450,
    "price_material_per_unit": 17,
    "material_factor_per_unit": 0.10400000000000001
  },
  {
    "meps_id": "MEPS-2611524",
    "task_name_sv": "Innervägg, skarvspackling med remsa cc 90",
    "unit": "m2",
    "labor_norm_per_unit": 0.09,
    "surface_type": "vägg",
    "synonyms": "innervägg, skarvspackling med remsa cc 90;måla vägg;måla väggar;måla väggen;måla väggarna",
    "price_labor_per_hour": 450,
    "price_material_per_unit": 21,
    "material_factor_per_unit": 0.11699999999999999
  },
  {
    "meps_id": "MEPS-2611525",
    "task_name_sv": "Innervägg, bredspackling samt slipning, 1 gång",
    "unit": "m2",
    "labor_norm_per_unit": 0.08,
    "surface_type": "vägg",
    "synonyms": "innervägg, bredspackling samt slipning, 1 gång;måla vägg;måla väggar;måla väggen;måla väggarna",
    "price_labor_per_hour": 450,
    "price_material_per_unit": 66,
    "material_factor_per_unit": 0.10400000000000001
  },
  {
    "meps_id": "MEPS-2611526",
    "task_name_sv": "Innervägg, bredspackling samt slipning, 2 gånger",
    "unit": "m2",
    "labor_norm_per_unit": 0.16,
    "surface_type": "vägg",
    "synonyms": "innervägg, bredspackling samt slipning, 2 gånger;måla vägg;måla väggar;måla väggen;måla väggarna",
    "price_labor_per_hour": 450,
    "price_material_per_unit": 108,
    "material_factor_per_unit": 0.20800000000000002
  },
  {
    "meps_id": "MEPS-2611527",
    "task_name_sv": "Innervägg, bredspackling samt slipning, 3 gånger",
    "unit": "m2",
    "labor_norm_per_unit": 0.24,
    "surface_type": "vägg",
    "synonyms": "innervägg, bredspackling samt slipning, 3 gånger;måla vägg;måla väggar;måla väggen;måla väggarna",
    "price_labor_per_hour": 450,
    "price_material_per_unit": 150,
    "material_factor_per_unit": 0.312
  },
  {
    "meps_id": "MEPS-2611528",
    "task_name_sv": "Innervägg, grundning, 1 strykning",
    "unit": "m2",
    "labor_norm_per_unit": 0.03,
    "surface_type": "vägg",
    "default_layers": 1,
    "synonyms": "innervägg, grundning, 1 strykning;måla vägg;måla väggar;måla väggen;måla väggarna",
    "price_labor_per_hour": 450,
    "price_material_per_unit": 24,
    "material_factor_per_unit": 0.039
  },
  {
    "meps_id": "MEPS-2611529",
    "task_name_sv": "Innervägg, isoler-/spärrmålning, 1 strykning",
    "unit": "m2",
    "labor_norm_per_unit": 0.08,
    "surface_type": "vägg",
    "default_layers": 1,
    "synonyms": "innervägg, isoler-/spärrmålning, 1 strykning;innervägg, isoler-/spärrmåla, 1 strykning;innervägg, isoler-/spärrtäckmåla, 1 strykning;innervägg, isoler-/spärrfärg, 1 strykning;måla vägg;måla väggar;måla väggen;måla väggarna",
    "price_labor_per_hour": 450,
    "price_material_per_unit": 26,
    "material_factor_per_unit": 0.10400000000000001
  },
  {
    "meps_id": "MEPS-2611530",
    "task_name_sv": "Innervägg, isoler-/spärrmålning, 2 strykningar",
    "unit": "m2",
    "labor_norm_per_unit": 0.16,
    "surface_type": "vägg",
    "default_layers": 2,
    "synonyms": "innervägg, isoler-/spärrmålning, 2 strykningar;innervägg, isoler-/spärrmåla, 2 strykningar;innervägg, isoler-/spärrtäckmåla, 2 strykningar;innervägg, isoler-/spärrfärg, 2 strykningar;måla vägg;måla väggar;måla väggen;måla väggarna",
    "price_labor_per_hour": 450,
    "price_material_per_unit": 48,
    "material_factor_per_unit": 0.20800000000000002
  },
  {
    "meps_id": "MEPS-2611531",
    "task_name_sv": "Innervägg, renoveringsduk",
    "unit": "m2",
    "labor_norm_per_unit": 0.16,
    "surface_type": "vägg",
    "synonyms": "innervägg, renoveringsduk;måla vägg;måla väggar;måla väggen;måla väggarna",
    "price_labor_per_hour": 450,
    "price_material_per_unit": 78,
    "material_factor_per_unit": 0.20800000000000002
  },
  {
    "meps_id": "MEPS-2611532",
    "task_name_sv": "Innervägg, målning, 1 strykning akrylat",
    "unit": "m2",
    "labor_norm_per_unit": 0.07,
    "surface_type": "vägg",
    "default_layers": 1,
    "synonyms": "innervägg, målning, 1 strykning akrylat;innervägg, måla, 1 strykning akrylat;innervägg, täckmåla, 1 strykning akrylat;innervägg, färg, 1 strykning akrylat;måla vägg;måla väggar;måla väggen;måla väggarna",
    "price_labor_per_hour": 450,
    "price_material_per_unit": 22,
    "material_factor_per_unit": 0.09100000000000001
  },
  {
    "meps_id": "MEPS-2611533",
    "task_name_sv": "Innervägg, målning, 2 strykningar akrylat",
    "unit": "m2",
    "labor_norm_per_unit": 0.09,
    "surface_type": "vägg",
    "default_layers": 2,
    "synonyms": "innervägg, målning, 2 strykningar akrylat;innervägg, måla, 2 strykningar akrylat;innervägg, täckmåla, 2 strykningar akrylat;innervägg, färg, 2 strykningar akrylat;måla vägg;måla väggar;måla väggen;måla väggarna",
    "price_labor_per_hour": 450,
    "price_material_per_unit": 37,
    "material_factor_per_unit": 0.11699999999999999
  },
  {
    "meps_id": "MEPS-2611534",
    "task_name_sv": "Innervägg, målning, 3 strykningar akrylat",
    "unit": "m2",
    "labor_norm_per_unit": 0.11,
    "surface_type": "vägg",
    "default_layers": 3,
    "synonyms": "innervägg, målning, 3 strykningar akrylat;innervägg, måla, 3 strykningar akrylat;innervägg, täckmåla, 3 strykningar akrylat;innervägg, färg, 3 strykningar akrylat;måla vägg;måla väggar;måla väggen;måla väggarna",
    "price_labor_per_hour": 450,
    "price_material_per_unit": 52,
    "material_factor_per_unit": 0.14300000000000002
  },
  {
    "meps_id": "MEPS-2641523",
    "task_name_sv": "Innervägg, sprutmålning, 1 sprutning akrylat",
    "unit": "m2",
    "labor_norm_per_unit": 0.04,
    "surface_type": "vägg",
    "synonyms": "innervägg, sprutmålning, 1 sprutning akrylat;innervägg, sprutmåla, 1 sprutning akrylat;innervägg, spruttäckmåla, 1 sprutning akrylat;innervägg, sprutfärg, 1 sprutning akrylat;måla vägg;måla väggar;måla väggen;måla väggarna",
    "price_labor_per_hour": 450,
    "price_material_per_unit": 23,
    "material_factor_per_unit": 0.052000000000000005
  },
  {
    "meps_id": "MEPS-2671523",
    "task_name_sv": "Innervägg, sprutmålning, 2 sprutningar akrylat",
    "unit": "m2",
    "labor_norm_per_unit": 0.08,
    "surface_type": "vägg",
    "synonyms": "innervägg, sprutmålning, 2 sprutningar akrylat;innervägg, sprutmåla, 2 sprutningar akrylat;innervägg, spruttäckmåla, 2 sprutningar akrylat;innervägg, sprutfärg, 2 sprutningar akrylat;måla vägg;måla väggar;måla väggen;måla väggarna",
    "price_labor_per_hour": 450,
    "price_material_per_unit": 46,
    "material_factor_per_unit": 0.10400000000000001
  },
  {
    "meps_id": "MEPS-2701523",
    "task_name_sv": "Innervägg, sprutmålning, 3 sprutningar akrylat",
    "unit": "m2",
    "labor_norm_per_unit": 0.11,
    "surface_type": "vägg",
    "synonyms": "innervägg, sprutmålning, 3 sprutningar akrylat;innervägg, sprutmåla, 3 sprutningar akrylat;innervägg, spruttäckmåla, 3 sprutningar akrylat;innervägg, sprutfärg, 3 sprutningar akrylat;måla vägg;måla väggar;måla väggen;måla väggarna",
    "price_labor_per_hour": 450,
    "price_material_per_unit": 70,
    "material_factor_per_unit": 0.14300000000000002
  },
  {
    "meps_id": "MEPS-2731523",
    "task_name_sv": "Innervägg, tapet Non-Woven",
    "unit": "m2",
    "labor_norm_per_unit": 0.12,
    "surface_type": "vägg",
    "synonyms": "innervägg, tapet non-woven;måla vägg;måla väggar;måla väggen;måla väggarna",
    "price_labor_per_hour": 450,
    "price_material_per_unit": 64,
    "material_factor_per_unit": 0.156
  },
  {
    "meps_id": "MEPS-2731524",
    "task_name_sv": "Innervägg, tapet papper",
    "unit": "m2",
    "labor_norm_per_unit": 0.18,
    "surface_type": "vägg",
    "synonyms": "innervägg, tapet papper;måla vägg;måla väggar;måla väggen;måla väggarna",
    "price_labor_per_hour": 450,
    "price_material_per_unit": 52,
    "material_factor_per_unit": 0.23399999999999999
  },
  {
    "meps_id": "MEPS-2761523",
    "task_name_sv": "Dörr, karm, smyg och foder, slät, målning, 2 strykningar",
    "unit": "st",
    "labor_norm_per_unit": 0.72,
    "surface_type": "dörr",
    "default_layers": 2,
    "synonyms": "dörr, karm, smyg och foder, slät, målning, 2 strykningar;dörr, karm, smyg och foder, slät, måla, 2 strykningar;dörr, karm, smyg och foder, slät, täckmåla, 2 strykningar;dörr, karm, smyg och foder, slät, färg, 2 strykningar;måla dörr;måla dörren;måla dörrar;måla dörrarna",
    "price_labor_per_hour": 450,
    "price_material_per_unit": 214,
    "material_factor_per_unit": 0.9359999999999999
  },
  {
    "meps_id": "MEPS-2791523",
    "task_name_sv": "Fönster 10×12 med fönsterbågar, målning med täckfärg, 1 strykning",
    "unit": "st",
    "labor_norm_per_unit": 0.13,
    "surface_type": "fönster",
    "default_layers": 1,
    "synonyms": "fönster 10×12 med fönsterbågar, målning med täckfärg, 1 strykning;fönster 10×12 med fönsterbågar, målning med täckmålafärg, 1 strykning;fönster 10×12 med fönsterbågar, målning med målafärg, 1 strykning;fönster 10×12 med fönsterbågar, målning med målningfärg, 1 strykning;fönster 10×12 med fönsterbågar, måla med täckfärg, 1 strykning;fönster 10×12 med fönsterbågar, täckmåla med täckfärg, 1 strykning;fönster 10×12 med fönsterbågar, färg med täckfärg, 1 strykning;måla fönster;måla fönstret;måla fönstren",
    "price_labor_per_hour": 450,
    "price_material_per_unit": 40,
    "material_factor_per_unit": 0.169
  },
  {
    "meps_id": "MEPS-2791524",
    "task_name_sv": "Fönster, karm och smyg 0,9–1,7 m², målning med täckfärg, 1 strykning",
    "unit": "st",
    "labor_norm_per_unit": 0.64,
    "surface_type": "dörr",
    "default_layers": 1,
    "synonyms": "fönster, karm och smyg 0,9–1,7 m², målning med täckfärg, 1 strykning;fönster, karm och smyg 0,9–1,7 m², målning med täckmålafärg, 1 strykning;fönster, karm och smyg 0,9–1,7 m², målning med målafärg, 1 strykning;fönster, karm och smyg 0,9–1,7 m², målning med målningfärg, 1 strykning;fönster, karm och smyg 0,9–1,7 m², måla med täckfärg, 1 strykning;fönster, karm och smyg 0,9–1,7 m², täckmåla med täckfärg, 1 strykning;fönster, karm och smyg 0,9–1,7 m², färg med täckfärg, 1 strykning;måla dörr;måla dörren;måla dörrar;måla dörrarna",
    "price_labor_per_hour": 450,
    "price_material_per_unit": 56,
    "material_factor_per_unit": 0.8320000000000001
  },
  {
    "meps_id": "MEPS-2881523",
    "task_name_sv": "Golvsockel, slät, i- och påspackling samt slipning",
    "unit": "lpm",
    "labor_norm_per_unit": 0.06,
    "surface_type": "golv",
    "synonyms": "golvsockel, slät, i- och påspackling samt slipning;måla golv;måla golvet",
    "price_labor_per_hour": 450,
    "price_material_per_unit": 1.62,
    "material_factor_per_unit": 0.078
  },
  {
    "meps_id": "MEPS-2881524",
    "task_name_sv": "Golvsockel, slät, bredspackling samt slipning, 1 gång",
    "unit": "lpm",
    "labor_norm_per_unit": 0.02,
    "surface_type": "golv",
    "synonyms": "golvsockel, slät, bredspackling samt slipning, 1 gång;måla golv;måla golvet",
    "price_labor_per_hour": 450,
    "price_material_per_unit": 8,
    "material_factor_per_unit": 0.026000000000000002
  },
  {
    "meps_id": "MEPS-2881525",
    "task_name_sv": "Golvsockel, slät, bredspackling samt slipning, 2 gånger",
    "unit": "lpm",
    "labor_norm_per_unit": 0.04,
    "surface_type": "golv",
    "synonyms": "golvsockel, slät, bredspackling samt slipning, 2 gånger;måla golv;måla golvet",
    "price_labor_per_hour": 450,
    "price_material_per_unit": 13.2,
    "material_factor_per_unit": 0.052000000000000005
  },
  {
    "meps_id": "MEPS-2881526",
    "task_name_sv": "Golvsockel, slät, grundning, 1 strykning",
    "unit": "lpm",
    "labor_norm_per_unit": 0.02,
    "surface_type": "golv",
    "default_layers": 1,
    "synonyms": "golvsockel, slät, grundning, 1 strykning;måla golv;måla golvet",
    "price_labor_per_hour": 450,
    "price_material_per_unit": 4.32,
    "material_factor_per_unit": 0.026000000000000002
  },
  {
    "meps_id": "MEPS-2881528",
    "task_name_sv": "Golvsockel, slät, schellackering",
    "unit": "lpm",
    "labor_norm_per_unit": 0.01,
    "surface_type": "golv",
    "synonyms": "golvsockel, slät, schellackering;måla golv;måla golvet",
    "price_labor_per_hour": 450,
    "price_material_per_unit": 4.8,
    "material_factor_per_unit": 0.013000000000000001
  },
  {
    "meps_id": "MEPS-2881529",
    "task_name_sv": "Golvsockel, slät, målning, 1 strykning",
    "unit": "lpm",
    "labor_norm_per_unit": 0.04,
    "surface_type": "golv",
    "default_layers": 1,
    "synonyms": "golvsockel, slät, målning, 1 strykning;golvsockel, slät, måla, 1 strykning;golvsockel, slät, täckmåla, 1 strykning;golvsockel, slät, färg, 1 strykning;måla golv;måla golvet",
    "price_labor_per_hour": 450,
    "price_material_per_unit": 13.26,
    "material_factor_per_unit": 0.052000000000000005
  },
  {
    "meps_id": "MEPS-2881530",
    "task_name_sv": "Golvsockel, slät, målning, 2 strykningar",
    "unit": "lpm",
    "labor_norm_per_unit": 0.05,
    "surface_type": "golv",
    "default_layers": 2,
    "synonyms": "golvsockel, slät, målning, 2 strykningar;golvsockel, slät, måla, 2 strykningar;golvsockel, slät, täckmåla, 2 strykningar;golvsockel, slät, färg, 2 strykningar;måla golv;måla golvet",
    "price_labor_per_hour": 450,
    "price_material_per_unit": 19,
    "material_factor_per_unit": 0.065
  },
  {
    "meps_id": "MEPS-2881531",
    "task_name_sv": "Golvsockel, slät, målning, 3 strykningar",
    "unit": "lpm",
    "labor_norm_per_unit": 0.06,
    "surface_type": "golv",
    "default_layers": 3,
    "synonyms": "golvsockel, slät, målning, 3 strykningar;golvsockel, slät, måla, 3 strykningar;golvsockel, slät, täckmåla, 3 strykningar;golvsockel, slät, färg, 3 strykningar;måla golv;måla golvet",
    "price_labor_per_hour": 450,
    "price_material_per_unit": 25.3,
    "material_factor_per_unit": 0.078
  },
  {
    "meps_id": "MEPS-2881532",
    "task_name_sv": "Golvsockel, profil, i- och påspackling samt slipning",
    "unit": "lpm",
    "labor_norm_per_unit": 0.08,
    "surface_type": "golv",
    "synonyms": "golvsockel, profil, i- och påspackling samt slipning;måla golv;måla golvet",
    "price_labor_per_hour": 450,
    "price_material_per_unit": 1.62,
    "material_factor_per_unit": 0.10400000000000001
  },
  {
    "meps_id": "MEPS-2881533",
    "task_name_sv": "Golvsockel, profil, bredspackling samt slipning, 1 gång",
    "unit": "lpm",
    "labor_norm_per_unit": 0.15,
    "surface_type": "golv",
    "synonyms": "golvsockel, profil, bredspackling samt slipning, 1 gång;måla golv;måla golvet",
    "price_labor_per_hour": 450,
    "price_material_per_unit": 8,
    "material_factor_per_unit": 0.195
  },
  {
    "meps_id": "MEPS-2881534",
    "task_name_sv": "Golvsockel, profil, bredspackling samt slipning, 2 gånger",
    "unit": "lpm",
    "labor_norm_per_unit": 0.29,
    "surface_type": "golv",
    "synonyms": "golvsockel, profil, bredspackling samt slipning, 2 gånger;måla golv;måla golvet",
    "price_labor_per_hour": 450,
    "price_material_per_unit": 13.2,
    "material_factor_per_unit": 0.377
  },
  {
    "meps_id": "MEPS-2881535",
    "task_name_sv": "Golvsockel, profil, grundning, 1 strykning",
    "unit": "lpm",
    "labor_norm_per_unit": 0.02,
    "surface_type": "golv",
    "default_layers": 1,
    "synonyms": "golvsockel, profil, grundning, 1 strykning;måla golv;måla golvet",
    "price_labor_per_hour": 450,
    "price_material_per_unit": 4.3,
    "material_factor_per_unit": 0.026000000000000002
  },
  {
    "meps_id": "MEPS-2881536",
    "task_name_sv": "Golvsockel, profil, målning, 1 strykning",
    "unit": "lpm",
    "labor_norm_per_unit": 0.06,
    "surface_type": "golv",
    "default_layers": 1,
    "synonyms": "golvsockel, profil, målning, 1 strykning;golvsockel, profil, måla, 1 strykning;golvsockel, profil, täckmåla, 1 strykning;golvsockel, profil, färg, 1 strykning;måla golv;måla golvet",
    "price_labor_per_hour": 450,
    "price_material_per_unit": 13.2,
    "material_factor_per_unit": 0.078
  },
  {
    "meps_id": "MEPS-2881537",
    "task_name_sv": "Golvsockel, profil, målning, 2 strykningar",
    "unit": "lpm",
    "labor_norm_per_unit": 0.07,
    "surface_type": "golv",
    "default_layers": 2,
    "synonyms": "golvsockel, profil, målning, 2 strykningar;golvsockel, profil, måla, 2 strykningar;golvsockel, profil, täckmåla, 2 strykningar;golvsockel, profil, färg, 2 strykningar;måla golv;måla golvet",
    "price_labor_per_hour": 450,
    "price_material_per_unit": 19.3,
    "material_factor_per_unit": 0.09100000000000001
  },
  {
    "meps_id": "MEPS-2881538",
    "task_name_sv": "Golvsockel, profil, målning, 3 strykningar",
    "unit": "lpm",
    "labor_norm_per_unit": 0.08,
    "surface_type": "golv",
    "default_layers": 3,
    "synonyms": "golvsockel, profil, målning, 3 strykningar;golvsockel, profil, måla, 3 strykningar;golvsockel, profil, täckmåla, 3 strykningar;golvsockel, profil, färg, 3 strykningar;måla golv;måla golvet",
    "price_labor_per_hour": 450,
    "price_material_per_unit": 25,
    "material_factor_per_unit": 0.10400000000000001
  },
  {
    "meps_id": "MEPS-2911523",
    "task_name_sv": "Behandlad slät taklist, tvättning/borstning samt målning, 1 strykning",
    "unit": "lpm",
    "labor_norm_per_unit": 0.06,
    "surface_type": "tak",
    "default_layers": 1,
    "synonyms": "behandlad slät taklist, tvättning/borstning samt målning, 1 strykning;behandlad slät taklist, tvättning/borstning samt måla, 1 strykning;behandlad slät taklist, tvättning/borstning samt täckmåla, 1 strykning;behandlad slät taklist, tvättning/borstning samt färg, 1 strykning;behandla tak;behandla taket",
    "price_labor_per_hour": 450,
    "price_material_per_unit": 6.8,
    "material_factor_per_unit": 0.078
  },
  {
    "meps_id": "MEPS-2911524",
    "task_name_sv": "Obehandlad slät taklist, målning, 1 strykning",
    "unit": "lpm",
    "labor_norm_per_unit": 0.02,
    "surface_type": "tak",
    "default_layers": 1,
    "synonyms": "obehandlad slät taklist, målning, 1 strykning;obehandlad slät taklist, måla, 1 strykning;obehandlad slät taklist, täckmåla, 1 strykning;obehandlad slät taklist, färg, 1 strykning;behandla tak;behandla taket",
    "price_labor_per_hour": 450,
    "price_material_per_unit": 7.2,
    "material_factor_per_unit": 0.026000000000000002
  },
  {
    "meps_id": "MEPS-2911525",
    "task_name_sv": "Obehandlad slät taklist, målning, 2 strykningar",
    "unit": "lpm",
    "labor_norm_per_unit": 0.04,
    "surface_type": "tak",
    "default_layers": 2,
    "synonyms": "obehandlad slät taklist, målning, 2 strykningar;obehandlad slät taklist, måla, 2 strykningar;obehandlad slät taklist, täckmåla, 2 strykningar;obehandlad slät taklist, färg, 2 strykningar;behandla tak;behandla taket",
    "price_labor_per_hour": 450,
    "price_material_per_unit": 12,
    "material_factor_per_unit": 0.052000000000000005
  },
  {
    "meps_id": "MEPS-2911526",
    "task_name_sv": "Obehandlad slät taklist, målning, 3 strykningar",
    "unit": "lpm",
    "labor_norm_per_unit": 0.05,
    "surface_type": "tak",
    "default_layers": 3,
    "synonyms": "obehandlad slät taklist, målning, 3 strykningar;obehandlad slät taklist, måla, 3 strykningar;obehandlad slät taklist, täckmåla, 3 strykningar;obehandlad slät taklist, färg, 3 strykningar;behandla tak;behandla taket",
    "price_labor_per_hour": 450,
    "price_material_per_unit": 23,
    "material_factor_per_unit": 0.065
  },
  {
    "meps_id": "MEPS-2941523",
    "task_name_sv": "Målning innertak, isoler-/spärrmålning, 1 strykning",
    "unit": "m2",
    "labor_norm_per_unit": 0.29,
    "surface_type": "tak",
    "default_layers": 1,
    "synonyms": "målning innertak, isoler-/spärrmålning, 1 strykning;måla innertak, isoler-/spärrmålning, 1 strykning;täckmåla innertak, isoler-/spärrmålning, 1 strykning;färg innertak, isoler-/spärrmålning, 1 strykning;måla tak;måla taket",
    "price_labor_per_hour": 450,
    "price_material_per_unit": 46,
    "material_factor_per_unit": 0.377
  },
  {
    "meps_id": "MEPS-2971523",
    "task_name_sv": "Målning innertak, 1 strykning",
    "unit": "m2",
    "labor_norm_per_unit": 0.322,
    "surface_type": "tak",
    "default_layers": 1,
    "synonyms": "målning innertak, 1 strykning;måla innertak, 1 strykning;täckmåla innertak, 1 strykning;färg innertak, 1 strykning;måla tak;måla taket",
    "price_labor_per_hour": 450,
    "price_material_per_unit": 20,
    "material_factor_per_unit": 0.4186
  },
  {
    "meps_id": "MEPS-2971524",
    "task_name_sv": "Målning innertak, 2 strykningar",
    "unit": "m2",
    "labor_norm_per_unit": 0.39,
    "surface_type": "tak",
    "default_layers": 2,
    "synonyms": "målning innertak, 2 strykningar;måla innertak, 2 strykningar;täckmåla innertak, 2 strykningar;färg innertak, 2 strykningar;måla tak;måla taket",
    "price_labor_per_hour": 450,
    "price_material_per_unit": 32.4,
    "material_factor_per_unit": 0.507
  },
  {
    "meps_id": "MEPS-2971525",
    "task_name_sv": "Målning innertak, 3 strykningar",
    "unit": "m2",
    "labor_norm_per_unit": 0.43,
    "surface_type": "tak",
    "default_layers": 3,
    "synonyms": "målning innertak, 3 strykningar;måla innertak, 3 strykningar;täckmåla innertak, 3 strykningar;färg innertak, 3 strykningar;måla tak;måla taket",
    "price_labor_per_hour": 450,
    "price_material_per_unit": 39,
    "material_factor_per_unit": 0.559
  },
  {
    "meps_id": "MEPS-3001523",
    "task_name_sv": "Målning innertak, 1 strykning (ingen täckning)",
    "unit": "m2",
    "labor_norm_per_unit": 0.08,
    "surface_type": "tak",
    "default_layers": 1,
    "synonyms": "målning innertak, 1 strykning (ingen täckning);målning innertak, 1 strykning (ingen täckmålaning);målning innertak, 1 strykning (ingen målaning);målning innertak, 1 strykning (ingen målningning);måla innertak, 1 strykning (ingen täckning);täckmåla innertak, 1 strykning (ingen täckning);färg innertak, 1 strykning (ingen täckning);måla tak;måla taket",
    "price_labor_per_hour": 450,
    "price_material_per_unit": 10,
    "material_factor_per_unit": 0.10400000000000001
  },
  {
    "meps_id": "MEPS-3001525",
    "task_name_sv": "Målning innertak, isoler-/spärrmålning, 1 strykning (ingen täckning)",
    "unit": "m2",
    "labor_norm_per_unit": 0.08,
    "surface_type": "tak",
    "default_layers": 1,
    "synonyms": "målning innertak, isoler-/spärrmålning, 1 strykning (ingen täckning);målning innertak, isoler-/spärrmålning, 1 strykning (ingen täckmålaning);målning innertak, isoler-/spärrmålning, 1 strykning (ingen målaning);målning innertak, isoler-/spärrmålning, 1 strykning (ingen målningning);måla innertak, isoler-/spärrmålning, 1 strykning (ingen täckning);täckmåla innertak, isoler-/spärrmålning, 1 strykning (ingen täckning);färg innertak, isoler-/spärrmålning, 1 strykning (ingen täckning);måla tak;måla taket",
    "price_labor_per_hour": 450,
    "price_material_per_unit": 36,
    "material_factor_per_unit": 0.10400000000000001
  },
  {
    "meps_id": "MEPS-3001526",
    "task_name_sv": "Målning innertak, 2 strykningar (ingen täckning)",
    "unit": "m2",
    "labor_norm_per_unit": 0.24,
    "surface_type": "tak",
    "default_layers": 2,
    "synonyms": "målning innertak, 2 strykningar (ingen täckning);målning innertak, 2 strykningar (ingen täckmålaning);målning innertak, 2 strykningar (ingen målaning);målning innertak, 2 strykningar (ingen målningning);måla innertak, 2 strykningar (ingen täckning);täckmåla innertak, 2 strykningar (ingen täckning);färg innertak, 2 strykningar (ingen täckning);måla tak;måla taket",
    "price_labor_per_hour": 450,
    "price_material_per_unit": 29,
    "material_factor_per_unit": 0.312
  },
  {
    "meps_id": "MEPS-3001527",
    "task_name_sv": "Målning innertak, 3 strykningar (ingen täckning)",
    "unit": "m2",
    "labor_norm_per_unit": 0.16,
    "surface_type": "tak",
    "default_layers": 3,
    "synonyms": "målning innertak, 3 strykningar (ingen täckning);målning innertak, 3 strykningar (ingen täckmålaning);målning innertak, 3 strykningar (ingen målaning);målning innertak, 3 strykningar (ingen målningning);måla innertak, 3 strykningar (ingen täckning);täckmåla innertak, 3 strykningar (ingen täckning);färg innertak, 3 strykningar (ingen täckning);måla tak;måla taket",
    "price_labor_per_hour": 450,
    "price_material_per_unit": 22.4,
    "material_factor_per_unit": 0.20800000000000002
  },
  {
    "meps_id": "MEPS-3031523",
    "task_name_sv": "Rivning innervägg, tapetyta, rensning",
    "unit": "m2",
    "labor_norm_per_unit": 0.01,
    "surface_type": "vägg",
    "synonyms": "rivning innervägg, tapetyta, rensning;måla vägg;måla väggar;måla väggen;måla väggarna",
    "price_labor_per_hour": 450,
    "price_material_per_unit": 0,
    "material_factor_per_unit": 0.013000000000000001
  },
  {
    "meps_id": "MEPS-3061523",
    "task_name_sv": "Mjukfogning av innertak",
    "unit": "lpm",
    "labor_norm_per_unit": 0.04,
    "surface_type": "tak",
    "synonyms": "mjukfogning av innertak;måla tak;måla taket",
    "price_labor_per_hour": 450,
    "price_material_per_unit": 22,
    "material_factor_per_unit": 0.052000000000000005
  },
  {
    "meps_id": "MEPS-3091523",
    "task_name_sv": "Mjukfogning av innertak inklusive tejpning",
    "unit": "lpm",
    "labor_norm_per_unit": 0.07,
    "surface_type": "tak",
    "synonyms": "mjukfogning av innertak inklusive tejpning;måla tak;måla taket",
    "price_labor_per_hour": 450,
    "price_material_per_unit": 29,
    "material_factor_per_unit": 0.09100000000000001
  },
  {
    "meps_id": "MEPS-3121523",
    "task_name_sv": "Rensning, tvättning och borstning av innertak",
    "unit": "m2",
    "labor_norm_per_unit": 0.02,
    "surface_type": "tak",
    "synonyms": "rensning, tvättning och borstning av innertak;måla tak;måla taket",
    "price_labor_per_hour": 450,
    "price_material_per_unit": 1.5,
    "material_factor_per_unit": 0.026000000000000002
  },
  {
    "meps_id": "MEPS-3151523",
    "task_name_sv": "Innervägg, listverk, slät, tvättning och borstning",
    "unit": "lpm",
    "labor_norm_per_unit": 0.02,
    "surface_type": "vägg",
    "synonyms": "innervägg, listverk, slät, tvättning och borstning;måla vägg;måla väggar;måla väggen;måla väggarna",
    "price_labor_per_hour": 450,
    "price_material_per_unit": 0.75,
    "material_factor_per_unit": 0.026000000000000002
  },
  {
    "meps_id": "MEPS-3181524",
    "task_name_sv": "Innervägg, i- och påspackling samt målning med två strykningar akrylatfärg",
    "unit": "m2",
    "labor_norm_per_unit": 0.12,
    "surface_type": "vägg",
    "synonyms": "innervägg, i- och påspackling samt målning med två strykningar akrylatfärg;innervägg, i- och påspackling samt måla med två strykningar akrylatfärg;innervägg, i- och påspackling samt täckmåla med två strykningar akrylatfärg;innervägg, i- och påspackling samt färg med två strykningar akrylatfärg;måla vägg;måla väggar;måla väggen;måla väggarna",
    "price_labor_per_hour": 450,
    "price_material_per_unit": 45.4,
    "material_factor_per_unit": 0.156
  },
  {
    "meps_id": "MEPS-3211523",
    "task_name_sv": "Golvsockel, slät, tvättning, rensning, i- och påspackling samt målning med två strykningar täckfärg",
    "unit": "lpm",
    "labor_norm_per_unit": 0.13,
    "surface_type": "golv",
    "synonyms": "golvsockel, slät, tvättning, rensning, i- och påspackling samt målning med två strykningar täckfärg;golvsockel, slät, tvättning, rensning, i- och påspackling samt målning med två strykningar målafärg;golvsockel, slät, tvättning, rensning, i- och påspackling samt måla med två strykningar täckfärg;golvsockel, slät, tvättning, rensning, i- och påspackling samt färg med två strykningar täckfärg;måla golv;måla golvet",
    "price_labor_per_hour": 450,
    "price_material_per_unit": 21.6,
    "material_factor_per_unit": 0.169
  },
  {
    "meps_id": "MEPS-3241523",
    "task_name_sv": "Golvsockel, profil, tvättning, rensning, i- och påspackling samt målning med två strykningar täckfärg",
    "unit": "lpm",
    "labor_norm_per_unit": 0.19,
    "surface_type": "golv",
    "synonyms": "golvsockel, profil, tvättning, rensning, i- och påspackling samt måla med två strykningar täckfärg;golvsockel, profil, tvättning, rensning, i- och påspackling samt färg med två strykningar täckfärg;måla golv;måla golvet",
    "price_labor_per_hour": 450,
    "price_material_per_unit": 21.6,
    "material_factor_per_unit": 0.24700000000000003
  },
  {
    "meps_id": "MEPS-3271523",
    "task_name_sv": "Innertak, i- och påspackling samt slipning, 2 gånger",
    "unit": "m2",
    "labor_norm_per_unit": 0.035,
    "surface_type": "tak",
    "synonyms": "innertak, i- och påspackling samt slipning, 2 gånger;måla tak;måla taket",
    "price_labor_per_hour": 450,
    "price_material_per_unit": 8.75,
    "material_factor_per_unit": 0.045500000000000006
  },
  {
    "meps_id": "MEPS-3301523",
    "task_name_sv": "Innertak, i- och påspackling samt målning med två strykningar akrylatfärg",
    "unit": "m2",
    "labor_norm_per_unit": 0.195,
    "surface_type": "tak",
    "synonyms": "innertak, i- och påspackling samt målning med två strykningar akrylatfärg;innertak, i- och påspackling samt måla med två strykningar akrylatfärg;innertak, i- och påspackling samt täckmåla med två strykningar akrylatfärg;innertak, i- och påspackling samt färg med två strykningar akrylatfärg;måla tak;måla taket",
    "price_labor_per_hour": 450,
    "price_material_per_unit": 31.15,
    "material_factor_per_unit": 0.2535
  },
  {
    "meps_id": "MEPS-3331523",
    "task_name_sv": "Innervägg, två bredspacklingar samt målning med två strykningar akrylatfärg",
    "unit": "m2",
    "labor_norm_per_unit": 0.25,
    "surface_type": "vägg",
    "synonyms": "innervägg, två bredspacklingar samt målning med två strykningar akrylatfärg;innervägg, två bredspacklingar samt måla med två strykningar akrylatfärg;innervägg, två bredspacklingar samt täckmåla med två strykningar akrylatfärg;innervägg, två bredspacklingar samt färg med två strykningar akrylatfärg;måla vägg;måla väggar;måla väggen;måla väggarna",
    "price_labor_per_hour": 450,
    "price_material_per_unit": 145,
    "material_factor_per_unit": 0.325
  },
  {
    "meps_id": "MEPS-3361523",
    "task_name_sv": "Dörr, karm, smyg och foder, tvättning, i- och påspackling samt målning med två strykningar täckfärg",
    "unit": "st",
    "labor_norm_per_unit": 1.12,
    "surface_type": "dörr",
    "synonyms": "dörr, karm, smyg och foder, tvättning, i- och påspackling samt målning med två strykningar täckfärg;dörr, karm, smyg och foder, tvättning, i- och påspackling samt målning med två strykningar målafärg;dörr, karm, smyg och foder, tvättning, i- och påspackling samt måla med två strykningar täckfärg;dörr, karm, smyg och foder, tvättning, i- och påspackling samt färg med två strykningar täckfärg;måla dörr;måla dörren;måla dörrar;måla dörrarna",
    "price_labor_per_hour": 450,
    "price_material_per_unit": 277,
    "material_factor_per_unit": 1.4560000000000002
  },
  {
    "meps_id": "MEPS-3391523",
    "task_name_sv": "Dörr, karm, smyg och foder (en sida), tvättning, i- och påspackling samt målning med två strykningar täckfärg",
    "unit": "st",
    "labor_norm_per_unit": 0.73,
    "surface_type": "dörr",
    "synonyms": "måla dörr;måla dörren;måla dörrar;måla dörrarna",
    "price_labor_per_hour": 450,
    "price_material_per_unit": 180,
    "material_factor_per_unit": 0.949
  },
  {
    "meps_id": "MEPS-3421524",
    "task_name_sv": "Innervägg, rensning, tvättning och borstning",
    "unit": "m2",
    "labor_norm_per_unit": 0.03,
    "surface_type": "vägg",
    "synonyms": "innervägg, rensning, tvättning och borstning;måla vägg;måla väggar;måla väggen;måla väggarna",
    "price_labor_per_hour": 450,
    "price_material_per_unit": 1.5,
    "material_factor_per_unit": 0.039
  },
  {
    "meps_id": "MEPS-3451523",
    "task_name_sv": "Innertak, i- och påspackling samt målning med två strykningar akrylatfärg (endast takmålning)",
    "unit": "m2",
    "labor_norm_per_unit": 0.51,
    "surface_type": "tak",
    "synonyms": "innertak, i- och påspackling samt målning med två strykningar akrylatfärg (endast takmålning);innertak, i- och påspackling samt måla med två strykningar akrylatfärg (endast takmålning);innertak, i- och påspackling samt täckmåla med två strykningar akrylatfärg (endast takmålning);innertak, i- och påspackling samt färg med två strykningar akrylatfärg (endast takmålning);måla tak;måla taket",
    "price_labor_per_hour": 450,
    "price_material_per_unit": 31.15,
    "material_factor_per_unit": 0.663
  },
  {
    "meps_id": "MEPS-3481523",
    "task_name_sv": "Mjukfogning av innertak och golv inklusive tejpning",
    "unit": "lpm",
    "labor_norm_per_unit": 0.14,
    "surface_type": "tak",
    "synonyms": "mjukfogning av innertak och golv inklusive tejpning;måla tak;måla taket",
    "price_labor_per_hour": 450,
    "price_material_per_unit": 58,
    "material_factor_per_unit": 0.18200000000000002
  },
  {
    "meps_id": "MEPS-3481524",
    "task_name_sv": "Mjukfogning av innertak och golv",
    "unit": "lpm",
    "labor_norm_per_unit": 0.08,
    "surface_type": "tak",
    "synonyms": "mjukfogning av innertak och golv;måla tak;måla taket",
    "price_labor_per_hour": 450,
    "price_material_per_unit": 44,
    "material_factor_per_unit": 0.10400000000000001
  }
]